ads/__init__.py
ads/cli.py
ads/config.py
ads/aqua/__init__.py
ads/aqua/app.py
ads/aqua/cli.py
ads/aqua/constants.py
ads/aqua/data.py
ads/aqua/ui.py
ads/aqua/version.json
ads/aqua/client/__init__.py
ads/aqua/client/client.py
ads/aqua/client/openai_client.py
ads/aqua/common/__init__.py
ads/aqua/common/decorator.py
ads/aqua/common/entities.py
ads/aqua/common/enums.py
ads/aqua/common/errors.py
ads/aqua/common/utils.py
ads/aqua/config/__init__.py
ads/aqua/config/container_config.py
ads/aqua/config/evaluation/__init__.py
ads/aqua/config/evaluation/evaluation_service_config.py
ads/aqua/config/utils/__init__.py
ads/aqua/config/utils/serializer.py
ads/aqua/dummy_data/icon.txt
ads/aqua/dummy_data/oci_model_deployments.json
ads/aqua/dummy_data/oci_models.json
ads/aqua/dummy_data/readme.md
ads/aqua/evaluation/__init__.py
ads/aqua/evaluation/constants.py
ads/aqua/evaluation/entities.py
ads/aqua/evaluation/errors.py
ads/aqua/evaluation/evaluation.py
ads/aqua/extension/__init__.py
ads/aqua/extension/aqua_ws_msg_handler.py
ads/aqua/extension/base_handler.py
ads/aqua/extension/common_handler.py
ads/aqua/extension/common_ws_msg_handler.py
ads/aqua/extension/deployment_handler.py
ads/aqua/extension/deployment_ws_msg_handler.py
ads/aqua/extension/errors.py
ads/aqua/extension/evaluation_handler.py
ads/aqua/extension/evaluation_ws_msg_handler.py
ads/aqua/extension/finetune_handler.py
ads/aqua/extension/model_handler.py
ads/aqua/extension/models_ws_msg_handler.py
ads/aqua/extension/ui_handler.py
ads/aqua/extension/ui_websocket_handler.py
ads/aqua/extension/utils.py
ads/aqua/extension/models/__init__.py
ads/aqua/extension/models/ws_models.py
ads/aqua/finetuning/__init__.py
ads/aqua/finetuning/constants.py
ads/aqua/finetuning/entities.py
ads/aqua/finetuning/finetuning.py
ads/aqua/model/__init__.py
ads/aqua/model/constants.py
ads/aqua/model/entities.py
ads/aqua/model/enums.py
ads/aqua/model/model.py
ads/aqua/model/utils.py
ads/aqua/modeldeployment/__init__.py
oracle_ads-2.14.5.dist-info/entry_points.txt
oracle_ads-2.14.5.dist-info/licenses/LICENSE.txt
oracle_ads-2.14.5.dist-info/WHEEL
oracle_ads-2.14.5.dist-info/METADATA
oracle_ads-2.14.5.dist-info/RECORD
